{
  "openapi": "3.0.1",
  "info": {
    "title": "ApiRest",
    "version": "1.0"
  },
  "paths": {
    "/MetodosIntegrales/trapecio/simple": {
      "post": {
        "tags": [
          "MetodosIntegrales"
        ],
        "requestBody": {
          "content": {
            "application/json": {
              "schema": {
                "$ref": "#/components/schemas/DatosEntrada"
              }
            },
            "text/json": {
              "schema": {
                "$ref": "#/components/schemas/DatosEntrada"
              }
            },
            "application/*+json": {
              "schema": {
                "$ref": "#/components/schemas/DatosEntrada"
              }
            }
          }
        },
        "responses": {
          "200": {
            "description": "OK",
            "content": {
              "text/plain": {
                "schema": {
                  "$ref": "#/components/schemas/DatosSalida"
                }
              },
              "application/json": {
                "schema": {
                  "$ref": "#/components/schemas/DatosSalida"
                }
              },
              "text/json": {
                "schema": {
                  "$ref": "#/components/schemas/DatosSalida"
                }
              }
            }
          }
        }
      }
    },
    "/MetodosIntegrales/trapecio/multiple": {
      "post": {
        "tags": [
          "MetodosIntegrales"
        ],
        "requestBody": {
          "content": {
            "application/json": {
              "schema": {
                "$ref": "#/components/schemas/DatosEntrada"
              }
            },
            "text/json": {
              "schema": {
                "$ref": "#/components/schemas/DatosEntrada"
              }
            },
            "application/*+json": {
              "schema": {
                "$ref": "#/components/schemas/DatosEntrada"
              }
            }
          }
        },
        "responses": {
          "200": {
            "description": "OK",
            "content": {
              "text/plain": {
                "schema": {
                  "$ref": "#/components/schemas/DatosSalida"
                }
              },
              "application/json": {
                "schema": {
                  "$ref": "#/components/schemas/DatosSalida"
                }
              },
              "text/json": {
                "schema": {
                  "$ref": "#/components/schemas/DatosSalida"
                }
              }
            }
          }
        }
      }
    },
    "/MetodosIntegrales/simpson/1-3/simple": {
      "post": {
        "tags": [
          "MetodosIntegrales"
        ],
        "requestBody": {
          "content": {
            "application/json": {
              "schema": {
                "$ref": "#/components/schemas/DatosEntrada"
              }
            },
            "text/json": {
              "schema": {
                "$ref": "#/components/schemas/DatosEntrada"
              }
            },
            "application/*+json": {
              "schema": {
                "$ref": "#/components/schemas/DatosEntrada"
              }
            }
          }
        },
        "responses": {
          "200": {
            "description": "OK",
            "content": {
              "text/plain": {
                "schema": {
                  "$ref": "#/components/schemas/DatosSalida"
                }
              },
              "application/json": {
                "schema": {
                  "$ref": "#/components/schemas/DatosSalida"
                }
              },
              "text/json": {
                "schema": {
                  "$ref": "#/components/schemas/DatosSalida"
                }
              }
            }
          }
        }
      }
    },
    "/MetodosIntegrales/simpson/1-3/multiple": {
      "post": {
        "tags": [
          "MetodosIntegrales"
        ],
        "requestBody": {
          "content": {
            "application/json": {
              "schema": {
                "$ref": "#/components/schemas/DatosEntrada"
              }
            },
            "text/json": {
              "schema": {
                "$ref": "#/components/schemas/DatosEntrada"
              }
            },
            "application/*+json": {
              "schema": {
                "$ref": "#/components/schemas/DatosEntrada"
              }
            }
          }
        },
        "responses": {
          "200": {
            "description": "OK",
            "content": {
              "text/plain": {
                "schema": {
                  "$ref": "#/components/schemas/DatosSalida"
                }
              },
              "application/json": {
                "schema": {
                  "$ref": "#/components/schemas/DatosSalida"
                }
              },
              "text/json": {
                "schema": {
                  "$ref": "#/components/schemas/DatosSalida"
                }
              }
            }
          }
        }
      }
    },
    "/MetodosIntegrales/simpson/3_8": {
      "post": {
        "tags": [
          "MetodosIntegrales"
        ],
        "requestBody": {
          "content": {
            "application/json": {
              "schema": {
                "$ref": "#/components/schemas/DatosEntrada"
              }
            },
            "text/json": {
              "schema": {
                "$ref": "#/components/schemas/DatosEntrada"
              }
            },
            "application/*+json": {
              "schema": {
                "$ref": "#/components/schemas/DatosEntrada"
              }
            }
          }
        },
        "responses": {
          "200": {
            "description": "OK",
            "content": {
              "text/plain": {
                "schema": {
                  "$ref": "#/components/schemas/DatosSalida"
                }
              },
              "application/json": {
                "schema": {
                  "$ref": "#/components/schemas/DatosSalida"
                }
              },
              "text/json": {
                "schema": {
                  "$ref": "#/components/schemas/DatosSalida"
                }
              }
            }
          }
        }
      }
    },
    "/MetodosIntegrales/combinados": {
      "post": {
        "tags": [
          "MetodosIntegrales"
        ],
        "requestBody": {
          "content": {
            "application/json": {
              "schema": {
                "$ref": "#/components/schemas/DatosEntrada"
              }
            },
            "text/json": {
              "schema": {
                "$ref": "#/components/schemas/DatosEntrada"
              }
            },
            "application/*+json": {
              "schema": {
                "$ref": "#/components/schemas/DatosEntrada"
              }
            }
          }
        },
        "responses": {
          "200": {
            "description": "OK",
            "content": {
              "text/plain": {
                "schema": {
                  "$ref": "#/components/schemas/DatosSalida"
                }
              },
              "application/json": {
                "schema": {
                  "$ref": "#/components/schemas/DatosSalida"
                }
              },
              "text/json": {
                "schema": {
                  "$ref": "#/components/schemas/DatosSalida"
                }
              }
            }
          }
        }
      }
    }
  },
  "components": {
    "schemas": {
      "DatosEntrada": {
        "type": "object",
        "properties": {
          "funcion": {
            "type": "string",
            "nullable": true
          },
          "xi": {
            "type": "number",
            "format": "double"
          },
          "xd": {
            "type": "number",
            "format": "double"
          },
          "cantSubIntervalos": {
            "type": "integer",
            "format": "int32"
          }
        },
        "additionalProperties": false
      },
      "DatosSalida": {
        "type": "object",
        "properties": {
          "area": {
            "type": "number",
            "format": "double"
          }
        },
        "additionalProperties": false
      }
    }
  }
}